coverage_diff/__init__.py
coverage_diff/__main__.py
coverage_diff/main.py
coverage_diff-0.0.8.data/data/LICENSE
coverage_diff-0.0.8.dist-info/LICENSE
coverage_diff-0.0.8.dist-info/METADATA
coverage_diff-0.0.8.dist-info/WHEEL
coverage_diff-0.0.8.dist-info/entry_points.txt
coverage_diff-0.0.8.dist-info/top_level.txt
coverage_diff-0.0.8.dist-info/RECORD
