Metadata-Version: 2.1
Name: coverage-diff
Version: 0.0.8
Summary: Show/check coverage only for changed files (between any git branches)
Home-page: https://github.com/strayge/coverage-diff
Author: strayge
Author-email: strayge@gmail.com
License: UNKNOWN
Platform: UNKNOWN
Classifier: Programming Language :: Python :: 3.6
Classifier: Programming Language :: Python :: 3.7
Classifier: Programming Language :: Python :: 3.8
Classifier: License :: OSI Approved :: MIT License
Requires-Python: >=3.6
Requires-Dist: coverage (>=4)
